deeplenstronomy/__init__.py
deeplenstronomy/check.py
deeplenstronomy/deeplenstronomy.py
deeplenstronomy/distributions.py
deeplenstronomy/image_generator.py
deeplenstronomy/input_reader.py
deeplenstronomy/special.py
deeplenstronomy/surveys.py
deeplenstronomy/timeseries.py
deeplenstronomy/utils.py
deeplenstronomy/visualize.py
deeplenstronomy-0.0.2.3.dist-info/AUTHORS.rst
deeplenstronomy-0.0.2.3.dist-info/LICENSE
deeplenstronomy-0.0.2.3.dist-info/METADATA
deeplenstronomy-0.0.2.3.dist-info/WHEEL
deeplenstronomy-0.0.2.3.dist-info/top_level.txt
deeplenstronomy-0.0.2.3.dist-info/RECORD
