Metadata-Version: 2.1
Name: deeplenstronomy
Version: 0.0.2.3
Summary: wrap lenstronomy for efficient simulation generation
Home-page: https://github.com/deepskies/deeplenstronomy
Author: DeepSkiesLab
Author-email: deepskieslab@gmail.com
License: MIT
Keywords: deeplenstronomy
Platform: UNKNOWN
Classifier: Development Status :: 5 - Production/Stable
Classifier: Intended Audience :: Developers
Classifier: License :: OSI Approved :: MIT License
Classifier: Natural Language :: English
Classifier: Programming Language :: Python :: 3
Classifier: Programming Language :: Python :: 3.7
Classifier: Programming Language :: Python :: Implementation :: PyPy
Requires-Dist: wheel (>=0.22)
Requires-Dist: scipy (>=1.5.2)
Requires-Dist: pandas (>=1.1.2)
Requires-Dist: numpy (>=1.19.1)
Requires-Dist: matplotlib (>=3.3.2)
Requires-Dist: astropy (>=4.0.1.post1)
Requires-Dist: h5py (>=2.10.0)
Requires-Dist: pyyaml (>=5.3.1)
Requires-Dist: mpmath (>=1.1.0)
Requires-Dist: future (>=0.18.2)
Requires-Dist: lenstronomy (>=1.6.0)
